yta_ai_pollinations/__init__.py
yta_ai_pollinations-0.0.1.dist-info/LICENSE
yta_ai_pollinations-0.0.1.dist-info/METADATA
yta_ai_pollinations-0.0.1.dist-info/WHEEL
yta_ai_pollinations-0.0.1.dist-info/RECORD
